<?xml version="1.0" encoding="utf-8"?>
<opml version="1.0">
<head>
    <title>livedoor Reader Subscriptions</title>
    <dateCreated>Mon, 22 Aug 2016 02:20:01 UTC</dateCreated>
    <ownerName>xfomax</ownerName>
</head>
<body>
<outline title="Subscriptions">
    <outline title="UIEvolution">
      <outline title="ニュース＆プレスリリース フィード" htmlUrl="http://www.uievolution.co.jp/news" type="rss" xmlUrl="http://www.uievolution.co.jp/news-xml" />
      <outline title="神は細部に宿り給う" htmlUrl="http://tkido.com/blog" type="rss" xmlUrl="http://tkido.com/blog/feed" />
      <outline title="Life is beautiful" htmlUrl="http://satoshi.blogs.com/life/" type="rss" xmlUrl="http://satoshi.blogs.com/life/index.rdf" />
    </outline>
    <outline title="WEB情報通信">
      <outline title="西尾泰和のはてなダイアリー" htmlUrl="http://d.hatena.ne.jp/nishiohirokazu/" type="rss" xmlUrl="http://d.hatena.ne.jp/nishiohirokazu/rss" />
      <outline title="scalaとか・・・" htmlUrl="http://d.hatena.ne.jp/xuwei/" type="rss" xmlUrl="http://d.hatena.ne.jp/xuwei/rss" />
      <outline title="アカベコマイリ" htmlUrl="http://akabeko.me/blog" type="rss" xmlUrl="http://akabeko.me/blog/feed/" />
      <outline title="Publickey" htmlUrl="http://www.publickey1.jp/" type="rss" xmlUrl="http://www.publickey1.jp/atom.xml" />
      <outline title="CodeZine:新着一覧" htmlUrl="http://codezine.jp/" type="rss" xmlUrl="http://rss.rssad.jp/rss/codezine/new/20/index.xml" />
      <outline title="言語ゲーム" htmlUrl="http://d.hatena.ne.jp/propella/" type="rss" xmlUrl="http://d.hatena.ne.jp/propella/rss" />
      <outline title="shi3zの長文日記" htmlUrl="http://d.hatena.ne.jp/shi3z/" type="rss" xmlUrl="http://d.hatena.ne.jp/shi3z/rss2" />
      <outline title="琥珀色の戯言" htmlUrl="http://d.hatena.ne.jp/fujipon/" type="rss" xmlUrl="http://d.hatena.ne.jp/fujipon/rss" />
      <outline title="ごんざれふ" htmlUrl="http://otsubo.info/blog" type="rss" xmlUrl="http://otsubo.info/blog/atom.xml" />
      <outline title="mizchi's blog" htmlUrl="http://mizchi.hatenablog.com/" type="rss" xmlUrl="http://mizchi.hatenablog.com/feed" />
      <outline title="tsudamblr" htmlUrl="http://tsuda.tumblr.com/" type="rss" xmlUrl="http://tsuda.tumblr.com/rss" />
      <outline title="柴田 芳樹 (Yoshiki Shibata)" htmlUrl="http://yshibata.blog.so-net.ne.jp/" type="rss" xmlUrl="http://yshibata.blog.so-net.ne.jp/index.rdf" />
      <outline title="レブログ！" htmlUrl="http://mclover.net/reblog" type="rss" xmlUrl="http://mclover.net/reblog/feed/" />
      <outline title="paiza開発日誌" htmlUrl="http://paiza.hatenablog.com/" type="rss" xmlUrl="http://paiza.hatenablog.com/feed" />
      <outline title="わたしが知らないスゴ本は、きっとあなたが読んでいる" htmlUrl="http://dain.cocolog-nifty.com/myblog/" type="rss" xmlUrl="http://dain.cocolog-nifty.com/myblog/atom.xml" />
      <outline title="Higepon’s blog" htmlUrl="http://d.hatena.ne.jp/higepon/" type="rss" xmlUrl="http://d.hatena.ne.jp/higepon/rss" />
      <outline title="POSTD" htmlUrl="http://postd.cc" type="rss" xmlUrl="http://postd.cc/feed/" />
      <outline title="GoTheDistance" htmlUrl="http://gothedistance.hatenadiary.jp/" type="rss" xmlUrl="http://gothedistance.hatenadiary.jp/feed" />
      <outline title="MechaAG" htmlUrl="https://mechaag.tumblr.com/" type="rss" xmlUrl="http://mechaag.tumblr.com/rss" />
      <outline title="クックパッド開発者ブログ" htmlUrl="http://techlife.cookpad.com/" type="rss" xmlUrl="http://techlife.cookpad.com/feed" />
      <outline title="めもめも" htmlUrl="http://enakai00.hatenablog.com/" type="rss" xmlUrl="http://enakai00.hatenablog.com/feed" />
      <outline title="Amazon Web Services ブログ" htmlUrl="https://aws.amazon.com/jp/blogs/news/" type="rss" xmlUrl="https://aws.amazon.com/jp/blogs/news/feed/" />
    </outline>
    <outline title="それにつけても金のほしさよ">
      <outline title="のりぞーの目指せ壱億円！" htmlUrl="http://blog.livedoor.jp/norizou2005/" type="rss" xmlUrl="http://blog.livedoor.jp/norizou2005/index.rdf" />
      <outline title="インデックス・ドライバー" htmlUrl="http://indexdriver.blog.shinobi.jp/" type="rss" xmlUrl="http://indexdriver.blog.shinobi.jp/RSS/" />
      <outline title="紅の鹿の日記" htmlUrl="http://cervorosso.blog.jp/" type="rss" xmlUrl="http://cervorosso.blog.jp/index.rdf" />
      <outline title="☆Harvey☆のHappy Value Life♪" htmlUrl="http://blog.livedoor.jp/harvey_1/" type="rss" xmlUrl="http://blog.livedoor.jp/harvey_1/index.rdf" />
      <outline title="ゲーム銘柄で一攫千金（旧　短期トレードで勝ちを重ねる）" htmlUrl="http://ameblo.jp/kirito-99/" type="rss" xmlUrl="http://rssblog.ameba.jp/kirito-99/rss20.xml" />
      <outline title="鴨とネギの投資生活" htmlUrl="http://plaza.rakuten.co.jp/100hajime/" type="rss" xmlUrl="http://api.plaza.rakuten.ne.jp/100hajime/rss/" />
      <outline title="lodestar的投資日記" htmlUrl="http://plaza.rakuten.co.jp/lodestar2006/" type="rss" xmlUrl="http://api.plaza.rakuten.ne.jp/lodestar2006/rss/" />
      <outline title="2020年への資産運用の旅  　　since 2011.7.18" htmlUrl="http://blog.livedoor.jp/taipon777/" type="rss" xmlUrl="http://blog.livedoor.jp/taipon777/index.rdf" />
      <outline title="若手サラリーマンのバリュー投資日記" htmlUrl="http://blog.livedoor.jp/kabu2013/" type="rss" xmlUrl="http://blog.livedoor.jp/kabu2013/index.rdf" />
      <outline title="つなわたりのまいにち（専業投資家日記）" htmlUrl="http://a1000miles.blog.fc2.com/" type="rss" xmlUrl="http://a1000miles.blog.fc2.com/?xml" />
      <outline title="医学と投資についての随想 (KAPPA)" htmlUrl="http://blog.livedoor.jp/kappa_ccw/" type="rss" xmlUrl="http://blog.livedoor.jp/kappa_ccw/index.rdf" />
      <outline title="七転八起" htmlUrl="http://diceawayfx.exblog.jp" type="rss" xmlUrl="http://diceawayfx.exblog.jp/index.xml" />
      <outline title="かぶ１０００投資日記" htmlUrl="http://plaza.rakuten.co.jp/kabu1000/" type="rss" xmlUrl="http://api.plaza.rakuten.ne.jp/kabu1000/rss/" />
      <outline title="Market Hack" htmlUrl="http://markethack.net/" type="rss" xmlUrl="http://markethack.net/atom.xml" />
      <outline title="iFund運用報告書" htmlUrl="http://ito1973.blogspot.com/" type="rss" xmlUrl="http://ito1973.blogspot.com/feeds/posts/default" />
      <outline title="帝国データバンク 大型倒産速報" htmlUrl="http://www.tdb.co.jp/tosan/jouhou.html" type="rss" xmlUrl="http://www.tdb.co.jp/rss/jouhou.rdf" />
      <outline title="株の話、経済の話、何の話だろう？" htmlUrl="http://kabukeizainani.blogspot.com/" type="rss" xmlUrl="http://kabukeizainani.blogspot.com/feeds/posts/default" />
      <outline title="ダルだぜ☆" htmlUrl="http://daru1986.jugem.jp/" type="rss" xmlUrl="http://daru1986.jugem.jp/?mode=rss" />
      <outline title="割安株投資研究所" htmlUrl="http://maropiko.hatenablog.com/" type="rss" xmlUrl="http://maropiko.hatenablog.com/rss" />
      <outline title="株式情報／キッチンカブー/株ステーション/" htmlUrl="http://rdsig.yahoo.co.jp/rss/l/blog/myblog/rss2/url/RV=1/RU=aHR0cDovL2Jsb2dzLnlhaG9vLmNvLmpwL2poamg3ag--" type="rss" xmlUrl="http://blogs.yahoo.co.jp/jhjh7j/rss.xml" />
      <outline title="インターネット界隈の事を調べるお" htmlUrl="http://takanoridayo.blog.shinobi.jp/" type="rss" xmlUrl="http://takanoridayo.blog.shinobi.jp/RSS/" />
      <outline title="亀吉の投資メモ" htmlUrl="http://blog.livedoor.jp/ichonan-investment/" type="rss" xmlUrl="http://blog.livedoor.jp/ichonan-investment/index.rdf" />
      <outline title="J.S.エコハのブログ" htmlUrl="http://kameleon-kameleon.blogspot.com/" type="rss" xmlUrl="http://kameleon-kameleon.blogspot.com/feeds/posts/default" />
      <outline title="アセマネの内定を蹴って自分で運用するブログ" htmlUrl="http://blog.livedoor.jp/toushika_y/" type="rss" xmlUrl="http://blog.livedoor.jp/toushika_y/index.rdf" />
      <outline title="ウチナーサラリーマンの投資・グルメブログ" htmlUrl="http://ameblo.jp/trick-bz/" type="rss" xmlUrl="http://rssblog.ameba.jp/trick-bz/rss20.xml" />
      <outline title="高等遊民の備忘録" htmlUrl="http://koutou-yumin.seesaa.net/" type="rss" xmlUrl="http://koutou-yumin.seesaa.net/index.rdf" />
      <outline title="ゆうゆー投資法" htmlUrl="http://yuyutoushi.blog.fc2.com/" type="rss" xmlUrl="http://yuyutoushi.blog.fc2.com/?xml" />
      <outline title="さらだ備忘録" htmlUrl="http://blog.livedoor.jp/saladbowl8/" type="rss" xmlUrl="http://blog.livedoor.jp/saladbowl8/index.rdf" />
      <outline title="みきまるの優待バリュー株日誌" htmlUrl="http://plaza.rakuten.co.jp/mikimaru71/" type="rss" xmlUrl="http://api.plaza.rakuten.ne.jp/mikimaru71/rss/" />
      <outline title="雅の日記～お気楽生活をめざして" htmlUrl="http://plaza.rakuten.co.jp/slowsheep/" type="rss" xmlUrl="http://api.plaza.rakuten.ne.jp/slowsheep/rss/" />
      <outline title="小型株投資の日記" htmlUrl="http://rdsig.yahoo.co.jp/rss/l/blog/myblog/rss2/url/RV=1/RU=aHR0cDovL2Jsb2dzLnlhaG9vLmNvLmpwL2dvcm9udGFfdG91c2hp" type="rss" xmlUrl="http://blogs.yahoo.co.jp/goronta_toushi/rss.xml" />
      <outline title="金のなる木を投資で増やそう" htmlUrl="http://moneytree7.blog48.fc2.com/" type="rss" xmlUrl="http://moneytree7.blog48.fc2.com/?xml" />
      <outline title="キリギリスのように暮らし、アリのように蓄える" htmlUrl="http://rdsig.yahoo.co.jp/rss/l/blog/myblog/rss2/url/RV=1/RU=aHR0cDovL2Jsb2dzLnlhaG9vLmNvLmpwL3Nva3JhdGVzdmFsdWU-" type="rss" xmlUrl="http://blogs.yahoo.co.jp/sokratesvalue/rss.xml" />
      <outline title="エセバリュー投資日記Ⅱ" htmlUrl="http://blog.livedoor.jp/iorino11/" type="rss" xmlUrl="http://blog.livedoor.jp/iorino11/index.rdf" />
      <outline title="Carnavalito Capital Management" htmlUrl="http://blog.livedoor.jp/carnavalito/" type="rss" xmlUrl="http://blog.livedoor.jp/carnavalito/index.rdf" />
      <outline title="YAMDAS現更新履歴" htmlUrl="http://d.hatena.ne.jp/yomoyomo/" type="rss" xmlUrl="http://d.hatena.ne.jp/yomoyomo/rss" />
      <outline title="成長株で億万長者" htmlUrl="http://growth-stock.blog.jp/" type="rss" xmlUrl="http://growth-stock.blog.jp/index.rdf" />
      <outline title="インデックス投資日記＠川崎" htmlUrl="http://longinv.blog103.fc2.com/" type="rss" xmlUrl="http://feeds.feedburner.com/fc2/evbz" />
      <outline title="GoldmanSacheeの優待株投資" htmlUrl="http://plaza.rakuten.co.jp/kabuffet963/" type="rss" xmlUrl="http://api.plaza.rakuten.ne.jp/kabuffet963/rss/" />
      <outline title="貯金生活。投資生活。" htmlUrl="http://moneyfreedom.blog21.fc2.com/" type="rss" xmlUrl="http://moneyfreedom.blog21.fc2.com/?xml" />
      <outline title="マ◯ーの虎　ハリマオの投資日記" htmlUrl="http://blog.livedoor.jp/harimau_kabu/" type="rss" xmlUrl="http://blog.livedoor.jp/harimau_kabu/index.rdf" />
      <outline title="投資逍遥" htmlUrl="http://plaza.rakuten.co.jp/seiyan36/" type="rss" xmlUrl="http://api.plaza.rakuten.ne.jp/seiyan36/rss/" />
      <outline title="投信で手堅くlay-up!（インデックス投資ブログ）" htmlUrl="http://www.lay-up.net" type="rss" xmlUrl="http://feeds2.feedburner.com/lay-up/rss" />
      <outline title="アダム・スミス２世の経済解説" htmlUrl="http://stockbondcurrency.blog.fc2.com/" type="rss" xmlUrl="http://stockbondcurrency.blog.fc2.com/?xml" />
      <outline title="思考の整理日記" htmlUrl="http://www.countand1.com/" type="rss" xmlUrl="http://www.countand1.com/feeds/posts/default" />
      <outline title="投資家くまの投資メモ" htmlUrl="http://investerbear.blog.fc2.com/" type="rss" xmlUrl="http://investerbear.blog.fc2.com/?xml" />
      <outline title="いもらうの立会外分売 分析予想" htmlUrl="http://bunbai-yosou.blogspot.com/" type="rss" xmlUrl="http://bunbai-yosou.blogspot.com/feeds/posts/default?alt=rss" />
      <outline title="ほいみんの　のんびり日記" htmlUrl="http://ameblo.jp/takechan/" type="rss" xmlUrl="http://rssblog.ameba.jp/takechan/rss20.xml" />
      <outline title="アーリーリタイヤへの道" htmlUrl="http://larkstongueaspic.blog.fc2.com/" type="rss" xmlUrl="http://larkstongueaspic.blog.fc2.com/?xml" />
      <outline title="消費せず働きもしない未来を歩む遊民の独白" htmlUrl="http://nonconsumption.com/" type="rss" xmlUrl="http://noneedbuy.blog.fc2.com/?xml" />
      <outline title="しょぼい・・・らすかぶ日記" htmlUrl="http://plaza.rakuten.co.jp/otsune2007/" type="rss" xmlUrl="http://api.plaza.rakuten.ne.jp/otsune2007/rss/" />
      <outline title="いつか子供に伝えたいお金の話" htmlUrl="http://mushitori.blog.fc2.com/" type="rss" xmlUrl="http://mushitori.blog.fc2.com/?xml" />
      <outline title="テレカ刑事" htmlUrl="http://ameblo.jp/rongtyan/" type="rss" xmlUrl="http://rssblog.ameba.jp/rongtyan/rss20.xml" />
      <outline title="東証Project" htmlUrl="http://blog.livedoor.jp/love_aeria/" type="rss" xmlUrl="http://blog.livedoor.jp/love_aeria/index.rdf" />
      <outline title="変わり者になろう  −　目指せナンバーワンよりオンリーワン！　−" htmlUrl="http://yumeokanaeyou.jugem.jp/" type="rss" xmlUrl="http://yumeokanaeyou.jugem.jp/?mode=rss" />
      <outline title="ほったらかし投資のまにまに" htmlUrl="http://toyop.net/" type="rss" xmlUrl="http://toyop.net/?xml" />
      <outline title="バリュー投資のすすめ　～思ってるやつと違うからな～" htmlUrl="http://blog.livedoor.jp/zawakamifund/" type="rss" xmlUrl="http://blog.livedoor.jp/zawakamifund/index.rdf" />
      <outline title="バフェット流バリュー株投資で資産形成＋" htmlUrl="http://mnt01.blogspot.com/" type="rss" xmlUrl="http://mnt01.blogspot.com/feeds/posts/default" />
      <outline title="１億円を貯めてみよう！chapter2" htmlUrl="http://ichiokuen-wo.jp" type="rss" xmlUrl="http://ichiokuen-wo.jp/blog/feed" />
      <outline title="あつまろのこだわり資産運用" htmlUrl="http://atsumaro.doorblog.jp/" type="rss" xmlUrl="http://atsumaro.doorblog.jp/index.rdf" />
      <outline title="100man1oku｜サラリーマンが100万円を1億円にする" htmlUrl="http://100man1oku.main.jp" type="rss" xmlUrl="http://100man1oku.main.jp/feed" />
      <outline title="個人投資家パフォーマンスランキング" htmlUrl="http://value-ranking.seesaa.net/" type="rss" xmlUrl="http://value-ranking.seesaa.net/index.rdf" />
      <outline title="吊られた男の投資ブログ (インデックス投資)" htmlUrl="http://www.tsurao.com/" type="rss" xmlUrl="http://www.tsurao.com/index.rdf" />
      <outline title="期待値で計るバリュー投資　無期限信用取引　有" htmlUrl="http://plaza.rakuten.co.jp/seigo182/" type="rss" xmlUrl="http://api.plaza.rakuten.ne.jp/seigo182/rss/" />
      <outline title="市況かぶ全力２階建" htmlUrl="http://kabumatome.doorblog.jp/" type="rss" xmlUrl="http://kabumatome.doorblog.jp/index.rdf" />
      <outline title="モラトリアムサラリーマンの長期投資株ブログ" htmlUrl="http://kabumoratorium.com/" type="rss" xmlUrl="http://kabumoratorium.com/?xml" />
      <outline title="梅屋敷商店街のランダム・ウォーカー（インデックス投資実践記）" htmlUrl="http://randomwalker.blog19.fc2.com/" type="rss" xmlUrl="http://randomwalker.blog19.fc2.com/?xml" />
      <outline title="rennyの備忘録 （投資信託をコツコツinvest　#k2k2）" htmlUrl="http://renny.jugem.jp/" type="rss" xmlUrl="http://renny.jugem.jp/?mode=rss" />
      <outline title="Memorandum" htmlUrl="http://akihirollin.zoku-sei.com/" type="rss" xmlUrl="http://akihirollin.zoku-sei.com/RSS/" />
      <outline title="かえるの気長な生活日記。" htmlUrl="http://kaeru.orio.jp/" type="rss" xmlUrl="http://feeds2.feedburner.com/jp/kaeru" />
      <outline title="矢向町（やこうまち）のインデックス投資家" htmlUrl="http://indexinvest.blog32.fc2.com/" type="rss" xmlUrl="http://indexinvest.blog32.fc2.com/?xml" />
      <outline title="多くの人には逆さに見えても #Investudy" htmlUrl="http://mazyoshisystemlabo.tumblr.com/" type="rss" xmlUrl="http://mazyoshisystemlabo.tumblr.com/rss" />
      <outline title="株ライフブログ" htmlUrl="http://www.kablife.com/wp" type="rss" xmlUrl="http://www.kablife.com/wp/feed/" />
      <outline title="Passiveな投資とActiveな未来" htmlUrl="http://pension.blog88.fc2.com/" type="rss" xmlUrl="http://pension.blog88.fc2.com/?xml" />
      <outline title="www9945の公開プロフィール" htmlUrl="http://plaza.rakuten.co.jp/www9945/" type="rss" xmlUrl="http://api.plaza.rakuten.ne.jp/www9945/rss/" />
      <outline title="21世紀投資" htmlUrl="http://ameblo.jp/v-com2/" type="rss" xmlUrl="http://rssblog.ameba.jp/v-com2/rss20.xml" />
      <outline title="サラリーマンが株式投資でセミリタイアを目指してみました。" htmlUrl="http://blog.livedoor.jp/kabu2oku/" type="rss" xmlUrl="http://blog.livedoor.jp/kabu2oku/index.rdf" />
      <outline title="幸せなお金持ち的日記" htmlUrl="http://thehappyman.blog.fc2.com/" type="rss" xmlUrl="http://thehappyman.blog.fc2.com/?xml" />
      <outline title="poohの毎日～40代アーリーリタイア夫婦の暮らし～" htmlUrl="http://pooh2013.blog.fc2.com/" type="rss" xmlUrl="http://pooh2013.blog.fc2.com/?xml" />
      <outline title="たけなか まさはる" htmlUrl="http://rdsig.yahoo.co.jp/rss/l/blog/myblog/rss2/url/RV=1/RU=aHR0cDovL2Jsb2dzLnlhaG9vLmNvLmpwL3Rha2VuYWthMTIyMQ--" type="rss" xmlUrl="http://blogs.yahoo.co.jp/takenaka1221/rss.xml" />
      <outline title="ヤマノ投信" htmlUrl="http://early-retire.com" type="rss" xmlUrl="http://early-retire.com/feed/atom" />
      <outline title="IPO初値予想/分析　IPOストライカーの投資ブログ！" htmlUrl="http://ipo-striker.com/" type="rss" xmlUrl="http://ipo-striker.com/index.rdf" />
      <outline title="There is no free lunch" htmlUrl="http://plaza.rakuten.co.jp/snoozer8888/" type="rss" xmlUrl="http://api.plaza.rakuten.ne.jp/snoozer8888/rss/" />
      <outline title="アーリーセミリタイア生活日記" htmlUrl="http://oniwasblog.seesaa.net/" type="rss" xmlUrl="http://oniwasblog.seesaa.net/index.rdf" />
      <outline title="ひでファンド" htmlUrl="http://plaza.rakuten.co.jp/hidefund/" type="rss" xmlUrl="http://api.plaza.rakuten.ne.jp/hidefund/rss/" />
      <outline title="スイングトレード ★ 日記." htmlUrl="http://blog.livedoor.jp/ss2286234570/" type="rss" xmlUrl="http://blog.livedoor.jp/ss2286234570/index.rdf" />
      <outline title="仙人の祈り" htmlUrl="http://senninn.blog.fc2.com/" type="rss" xmlUrl="http://senninn.blog.fc2.com/?xml" />
      <outline title="減らないお財布を持ってフィナンシャル・インディペンデンスをめざす仲間のコミュニティー" htmlUrl="http://plaza.rakuten.co.jp/lucky7lucky/" type="rss" xmlUrl="http://api.plaza.rakuten.ne.jp/lucky7lucky/rss/" />
      <outline title="RING×TRADE" htmlUrl="http://ameblo.jp/ringtrade/" type="rss" xmlUrl="http://rssblog.ameba.jp/ringtrade/rss20.xml" />
      <outline title="株をはじめる前に読むブログ" htmlUrl="http://kabuohazimeru.blog22.fc2.com/" type="rss" xmlUrl="http://kabuohazimeru.blog22.fc2.com/?xml" />
      <outline title="株主優待と高配当株を買い続ける株式投資ブログ" htmlUrl="http://kibinago7777.blogspot.com/" type="rss" xmlUrl="http://kibinago7777.blogspot.com/feeds/posts/default" />
      <outline title="たくの投資ノート" htmlUrl="http://plaza.rakuten.co.jp/taku1225/" type="rss" xmlUrl="http://api.plaza.rakuten.ne.jp/taku1225/rss/" />
      <outline title="ろくすけの長期投資の旅" htmlUrl="http://blog.goo.ne.jp/6_suke?fm=rss" type="rss" xmlUrl="http://blog.goo.ne.jp/6_suke/rss2.xml" />
      <outline title="コムストックの投機日記" htmlUrl="http://blog.livedoor.jp/hk_131/" type="rss" xmlUrl="http://blog.livedoor.jp/hk_131/index.rdf" />
      <outline title="投資の教科書" htmlUrl="http://toushi-kyokasho.com" type="rss" xmlUrl="http://toushi-kyokasho.com/feed/" />
      <outline title="株主優待でお得な生活♪" htmlUrl="http://blog.livedoor.jp/kowaremaru/" type="rss" xmlUrl="http://blog.livedoor.jp/kowaremaru/index.rdf" />
      <outline title="Porco Rosso Financial Weblog" htmlUrl="http://ningyocho.blogspot.com/" type="rss" xmlUrl="http://ningyocho.blogspot.com/feeds/posts/default" />
      <outline title="いもらうの負けない投資　【分析で相場に勝つ】" htmlUrl="http://imolau.blog99.fc2.com/" type="rss" xmlUrl="http://imolau.blog99.fc2.com/?xml" />
      <outline title="橘玲 公式サイト" htmlUrl="http://www.tachibana-akira.com" type="rss" xmlUrl="http://www.tachibana-akira.com/feed" />
      <outline title="「配当金を雪だるま式に増やす投資日記」 ～Dividend Snowball Investing～" htmlUrl="http://dividendsnowball.blogspot.com/" type="rss" xmlUrl="http://dividendsnowball.blogspot.com/feeds/posts/default" />
      <outline title="しがないディーラーのブログ" htmlUrl="http://ameblo.jp/tetsu219/" type="rss" xmlUrl="http://rssblog.ameba.jp/tetsu219/rss20.xml" />
      <outline title="みやの株主優待投資日記" htmlUrl="http://miyanokabu.blog.fc2.com/" type="rss" xmlUrl="http://miyanokabu.blog.fc2.com/?xml" />
      <outline title="NightWalker's Investment Blog" htmlUrl="http://nightwalker.cocolog-nifty.com/money/" type="rss" xmlUrl="http://nightwalker.cocolog-nifty.com/money/atom.xml" />
      <outline title="アゴウの日記" htmlUrl="http://blog.livedoor.jp/agou2/" type="rss" xmlUrl="http://blog.livedoor.jp/agou2/index.rdf" />
      <outline title="ホンネの資産運用セミナー（インデックス投資ブログ）" htmlUrl="http://genuinvest.net/" type="rss" xmlUrl="http://genuinvest.net/?mode=rss" />
      <outline title="ごまおファンド" htmlUrl="http://ameblo.jp/g0mao/" type="rss" xmlUrl="http://rssblog.ameba.jp/g0mao/rss20.xml" />
      <outline title="株でサラリーマン卒業" htmlUrl="http://kablog.doorblog.jp/" type="rss" xmlUrl="http://kablog.doorblog.jp/index.rdf" />
      <outline title="本日の増担保規制解除ライン" htmlUrl="http://masitan.blog.fc2.com/" type="rss" xmlUrl="http://masitan.blog.fc2.com/?xml" />
      <outline title="自由になりたくて47歳で会社を辞めたらこうなった" htmlUrl="http://www.iwannabefree.info" type="rss" xmlUrl="http://www.iwannabefree.info/feed/" />
      <outline title="株式投資で資産、早期3000万円を目指す" htmlUrl="http://aketemiyo-akazunoma.doorblog.jp/" type="rss" xmlUrl="http://aketemiyo-akazunoma.doorblog.jp/index.rdf" />
      <outline title="海外ETFで資産運用" htmlUrl="http://www.netemate.net/" type="rss" xmlUrl="http://ic.edge.jp/page2feed/http://www.netemate.net/" />
      <outline title="Noppin's stock cafe" htmlUrl="http://blog.livedoor.jp/noppin/" type="rss" xmlUrl="http://blog.livedoor.jp/noppin/index.rdf" />
      <outline title="てーげー投資ライフのすすめ！" htmlUrl="http://freepapa.enjyuku-blog.com" type="rss" xmlUrl="http://freepapa.enjyuku-blog.com/feed" />
      <outline title="The Goal" htmlUrl="http://matsunosuke.jp" type="rss" xmlUrl="http://matsunosuke.jp/feed/" />
      <outline title="かすみちゃんの株主優待日記" htmlUrl="http://blog.livedoor.jp/setuyaku999/" type="rss" xmlUrl="http://blog.livedoor.jp/setuyaku999/index.rdf" />
      <outline title="資産運用相談員kaoruの　　　　ちょっといい話" htmlUrl="http://kaoru-office.biz/" type="rss" xmlUrl="http://kaoru-office.biz/?xml" />
      <outline title="もっとお金の話がしたい" htmlUrl="http://www.money-motto.com" type="rss" xmlUrl="http://www.money-motto.com/feed/" />
      <outline title="白米っ式見せかけバリュー投資" htmlUrl="http://plaza.rakuten.co.jp/sooo0831/" type="rss" xmlUrl="http://api.plaza.rakuten.ne.jp/sooo0831/rss/" />
      <outline title="まつを。の投資日記" htmlUrl="http://matsuwo2005.blogspot.com/" type="rss" xmlUrl="http://matsuwo2005.blogspot.com/feeds/posts/default" />
      <outline title="マルサのブログ － 金の亡者を辱め" htmlUrl="http://ameblo.jp/sarashikubi/" type="rss" xmlUrl="http://rssblog.ameba.jp/sarashikubi/rss20.xml" />
      <outline title="牛さん熊さんブログ" htmlUrl="http://bullbear.exblog.jp" type="rss" xmlUrl="http://bullbear.exblog.jp/index.xml" />
      <outline title="DUKE。のサーフィンインベストメント" htmlUrl="http://investorduke.blog.fc2.com/" type="rss" xmlUrl="http://investorduke.blog.fc2.com/?xml" />
      <outline title="資金管理の掟" htmlUrl="http://blog.livedoor.jp/avexfreak/" type="rss" xmlUrl="http://blog.livedoor.jp/avexfreak/index.rdf" />
      <outline title="nextir35の気になる株ブログ" htmlUrl="http://kininarukabu.com" type="rss" xmlUrl="http://kininarukabu.com/feed/" />
      <outline title="年間生活費100万円！　36歳からのドケチリタイア日記" htmlUrl="http://blog.livedoor.jp/mushoku2006/" type="rss" xmlUrl="http://blog.livedoor.jp/mushoku2006/index.rdf" />
      <outline title="百年後のヴィンテージマンション" htmlUrl="http://sanoji1416.jugem.jp/" type="rss" xmlUrl="http://sanoji1416.jugem.jp/?mode=rss" />
      <outline title="マネーへっちゃら日記" htmlUrl="http://money.enjyuku-blog.com" type="rss" xmlUrl="http://money.enjyuku-blog.com/feed" />
      <outline title="フクリの海外ＥＴＦ長期投資ブログ" htmlUrl="http://etf-investment.com" type="rss" xmlUrl="http://etf-investment.com/?feed=rss2" />
      <outline title="株式・証券会社比較情報サイト 96ut.kabu" htmlUrl="http://kabu.96ut.com" type="rss" xmlUrl="http://kabu.96ut.com/feed/" />
      <outline title="IPO・新規公開株 – 株式・証券会社比較情報サイト 96ut.kabu" htmlUrl="http://kabu.96ut.com" type="rss" xmlUrl="http://kabu.96ut.com/article/category/ipo/feed/" />
      <outline title="cubの日記　年収100万円の楽しい海外生活術・台湾編" htmlUrl="http://www.cubmaga.com" type="rss" xmlUrl="http://www.cubmaga.com/feed/" />
      <outline title="IPO初値予想ブログなら、キムさんのIPO投資日記" htmlUrl="http://deskpower.blog80.fc2.com/" type="rss" xmlUrl="http://deskpower.blog80.fc2.com/?xml" />
      <outline title="家計＆資産管理マニュアル" htmlUrl="http://kakeibo.lay-up.net" type="rss" xmlUrl="http://kakeibo.lay-up.net/feed" />
      <outline title="日々是好日" htmlUrl="http://ameblo.jp/aqofbq/" type="rss" xmlUrl="http://rssblog.ameba.jp/aqofbq/rss20.xml" />
      <outline title="偏屈たぬきのへそまがり投資日記" htmlUrl="http://plaza.rakuten.co.jp/hananoyama/" type="rss" xmlUrl="http://api.plaza.rakuten.ne.jp/hananoyama/rss/" />
      <outline title="ケン坊の資産運用日記" htmlUrl="http://kenbou-invest.blog.jp/" type="rss" xmlUrl="http://kenbou-invest.blog.jp/index.rdf" />
      <outline title="My Way" htmlUrl="http://rdsig.yahoo.co.jp/rss/l/blog/myblog/rss2/url/RV=1/RU=aHR0cDovL2Jsb2dzLnlhaG9vLmNvLmpwL3Nha2tha3UyMDEz" type="rss" xmlUrl="http://blogs.yahoo.co.jp/sakkaku2013/rss.xml" />
      <outline title="勝藤史郎のブログ" htmlUrl="http://shirokatsufuji.blog.fc2.com/" type="rss" xmlUrl="http://shirokatsufuji.blog.fc2.com/?xml" />
      <outline title="DJあかいのマンション総研" htmlUrl="http://mansioninstitute.com" type="rss" xmlUrl="http://mansioninstitute.com/?feed=rss2" />
      <outline title="投資を楽しむ♪" htmlUrl="http://pixy10.org" type="rss" xmlUrl="http://www.pixy10.org/index.rdf" />
      <outline title="ふみネコ　【資産運用日々徒然〜生き延びる為のDesign〜】" htmlUrl="http://fuminekofumi.jugem.jp/" type="rss" xmlUrl="http://fuminekofumi.jugem.jp/?mode=rss" />
      <outline title="堀古英司の「米国株式の魅力」" htmlUrl="http://plaza.rakuten.co.jp/iswallstreet/" type="rss" xmlUrl="http://api.plaza.rakuten.ne.jp/iswallstreet/rss/" />
      <outline title="JOYのパーシャルオーナーへの道" htmlUrl="http://jpyowner.exblog.jp" type="rss" xmlUrl="http://jpyowner.exblog.jp/index.xml" />
      <outline title="aako01jpの株式で一発逆転　 ~個別ファンダ中心~" htmlUrl="http://aako01jp.blog.fc2.com/" type="rss" xmlUrl="http://aako01jp.blog.fc2.com/?xml" />
      <outline title="映画を見ながら株式投資" htmlUrl="http://blog.goo.ne.jp/livin_on_a_prayer?fm=rss" type="rss" xmlUrl="http://blog.goo.ne.jp/livin_on_a_prayer/index.rdf" />
      <outline title="株式投資入門" htmlUrl="http://blog.goo.ne.jp/cgpf-inoue0901?fm=rss" type="rss" xmlUrl="http://blog.goo.ne.jp/cgpf-inoue0901/index.rdf" />
      <outline title="すぽさん投資ぶろぐ" htmlUrl="http://www.spotoushi.net/" type="rss" xmlUrl="http://www.spotoushi.net/index.rdf" />
      <outline title="あらなみの里" htmlUrl="http://aranami718.blog.fc2.com/" type="rss" xmlUrl="http://aranami718.blog.fc2.com/?xml" />
      <outline title="21世紀投資の別館" htmlUrl="http://blog.livedoor.jp/vcom2/" type="rss" xmlUrl="http://blog.livedoor.jp/vcom2/index.rdf" />
      <outline title="１億円を貯めてみよう！chapter2" htmlUrl="http://ichiokuen-wo.jp" type="rss" xmlUrl="http://ichiokuen-wo.jp/feed" />
      <outline title="マンション購入を真剣に考えるブログ" htmlUrl="http://wangantower.com" type="rss" xmlUrl="http://wangantower.com/?feed=rss2" />
      <outline title="マンションの間取りや価格を言いたい放題!" htmlUrl="http://mansion-madori.com/" type="rss" xmlUrl="http://mansion-madori.com/?xml" />
      <outline title="ワイルドインベスターズ投資ブログ" htmlUrl="http://blog.livedoor.jp/contrarian65-wild/" type="rss" xmlUrl="http://blog.livedoor.jp/contrarian65-wild/index.rdf" />
      <outline title="インデックス投資家からの脱却      （アンチインデックス）" htmlUrl="http://anti-index.blog.jp/" type="rss" xmlUrl="http://anti-index.blog.jp/index.rdf" />
      <outline title="「株価プレス」" htmlUrl="http://kabu-press.com" type="rss" xmlUrl="http://kabu-press.com/feed/" />
      <outline title="ニュース屋さん＠日本株式投資" htmlUrl="http://news830.com" type="rss" xmlUrl="http://news830.com/feed" />
      <outline title="ヤマノ投信" htmlUrl="http://early-retire.com" type="rss" xmlUrl="http://early-retire.com/feed" />
      <outline title="Not-So-News" htmlUrl="http://nots.hatenablog.com/" type="rss" xmlUrl="http://nots.hatenablog.com/feed" />
      <outline title="マネーニュース2ch" htmlUrl="http://okanehadaiji.com/" type="rss" xmlUrl="http://okanehadaiji.com/index.rdf" />
      <outline title="中長期投資の練習記録" htmlUrl="http://tryinvesting.blog.fc2.com/" type="rss" xmlUrl="http://tryinvesting.blog.fc2.com/?xml" />
      <outline title="やまもといちろう 公式ブログ" htmlUrl="http://lineblog.me/yamamotoichiro/" type="rss" xmlUrl="http://lineblog.me/yamamotoichiro/index.rdf" />
      <outline title="エナフンさんの梨の木" htmlUrl="http://ameblo.jp/okuyama-tukito/" type="rss" xmlUrl="http://rssblog.ameba.jp/okuyama-tukito/rss20.xml" />
      <outline title="ドル使いの海外投資" htmlUrl="http://useusd.com" type="rss" xmlUrl="http://useusd.com/feed/" />
      <outline title="孤高のFXブログ" htmlUrl="http://fxria10.blog.fc2.com/" type="rss" xmlUrl="http://fxria10.blog.fc2.com/?xml" />
      <outline title="惣菜が愛した銘柄達" htmlUrl="http://gachihomoquartet.blog.fc2.com/" type="rss" xmlUrl="http://gachihomoquartet.blog.fc2.com/?xml" />
      <outline title="Power of Equity" htmlUrl="http://powerofequity.blogspot.com/" type="rss" xmlUrl="http://powerofequity.blogspot.com/feeds/posts/default" />
      <outline title="決算ダービー" htmlUrl="http://blog.livedoor.jp/kessanderby/" type="rss" xmlUrl="http://blog.livedoor.jp/kessanderby/index.rdf" />
      <outline title="うえけんの株式投資おぼえ書き" htmlUrl="http://value-investment.uekenweb.com" type="rss" xmlUrl="http://value-investment.uekenweb.com/feed/" />
    </outline>
    <outline title="まとめ">
      <outline title="Lovely Carving のブログ" htmlUrl="http://blog.lovely-carving.com/" type="rss" xmlUrl="http://blog.lovely-carving.com/?mode=rss" />
      <outline title="たんぷとん" htmlUrl="http://hepton-rk.tumblr.com/" type="rss" xmlUrl="http://hepton-rk.tumblr.com/rss" />
      <outline title="トマスの疑い深い資産運用" htmlUrl="http://foma.blog.jp/" type="rss" xmlUrl="http://foma.blog.jp/index.rdf" />
      <outline title="買いは家まで　売りは命まで" htmlUrl="http://ameblo.jp/iguru402/" type="rss" xmlUrl="http://rssblog.ameba.jp/iguru402/rss20.xml" />
      <outline title="まなめはうす-ニュースヘッドライン-" htmlUrl="http://homepage1.nifty.com/maname/" type="rss" xmlUrl="http://homepage1.nifty.com/maname/headline.rdf" />
      <outline title="CBlog" htmlUrl="http://www.career-bank.co.jp/weblog/" type="rss" xmlUrl="http://www.career-bank.co.jp/weblog/atom.xml" />
      <outline title="やしお" htmlUrl="http://d.hatena.ne.jp/Yashio/" type="rss" xmlUrl="http://d.hatena.ne.jp/Yashio/rss" />
      <outline title="KGRC" htmlUrl="http://kogumarecord.tumblr.com/" type="rss" xmlUrl="http://kogumarecord.tumblr.com/rss" />
    </outline>
    <outline title="アニメコミック">
      <outline title="電動脳髄ver.3" htmlUrl="http://touazyuukou.blog40.fc2.com/" type="rss" xmlUrl="http://touazyuukou.blog40.fc2.com/?xml" />
      <outline title="紙屋研究所" htmlUrl="http://d.hatena.ne.jp/kamiyakenkyujo/" type="rss" xmlUrl="http://d.hatena.ne.jp/kamiyakenkyujo/rss" />
      <outline title="沼の見える街" htmlUrl="http://numagasa.hatenablog.com/" type="rss" xmlUrl="http://numagasa.hatenablog.com/feed" />
      <outline title="スコシフシギな世界－藤子･F･不二雄ブログ" htmlUrl="http://plaza.rakuten.co.jp/neoreeves/" type="rss" xmlUrl="http://api.plaza.rakuten.ne.jp/neoreeves/rss/" />
    </outline>
    <outline title="ゲーム森羅万象">
      <outline title="minecraft" htmlUrl="http://minecraft.ologies.net" type="rss" xmlUrl="http://minecraft.ologies.net/feed/" />
      <outline title="マインクラフトてんやわんや開拓記" htmlUrl="http://zombiepigman.moe/" type="rss" xmlUrl="http://blog.livedoor.jp/zombiepigman/index.rdf" />
      <outline title="不倒城" htmlUrl="http://mubou.seesaa.net/" type="rss" xmlUrl="http://mubou.seesaa.net/index.rdf" />
      <outline title="スパ帝国" htmlUrl="http://spa-game.com" type="rss" xmlUrl="http://spa-game.com/?feed=rss2" />
      <outline title="ゲーム風呂" htmlUrl="http://udontaro.blog79.fc2.com/" type="rss" xmlUrl="http://udontaro.blog79.fc2.com/?xml" />
      <outline title="もぐらゲームス" htmlUrl="http://www.moguragames.com" type="rss" xmlUrl="http://www.moguragames.com/feed/" />
      <outline title="AUTOMATON" htmlUrl="http://jp.automaton.am" type="rss" xmlUrl="http://jp.automaton.am/feed/" />
      <outline title="マインクラフトPC版シックスパックで遊ぶブログ！" htmlUrl="http://minecraft-forpc.net" type="rss" xmlUrl="http://minecraft-forpc.net/feed/" />
      <outline title="あるぼるのゆるりとマイクラ日記" htmlUrl="http://arbor-mc.com" type="rss" xmlUrl="http://arbor-mc.com/feed/" />
      <outline title="Social Game Info" htmlUrl="http://gamebiz.jp" type="rss" xmlUrl="http://gamebiz.jp/?feed=rss" />
    </outline>
    <outline title="政治経済社会">
      <outline title="石壁に百合の花咲く" htmlUrl="http://www.ishiyuri.com/" type="rss" xmlUrl="http://www.ishiyuri.com/feed" />
      <outline title="山形浩生の「経済のトリセツ」" htmlUrl="http://cruel.hatenablog.com/" type="rss" xmlUrl="http://d.hatena.ne.jp/wlj-Friday/rss" />
      <outline title="Follow the accident. Fear the set plan." htmlUrl="https://ys347.wordpress.com" type="rss" xmlUrl="http://ys347.wordpress.com/feed/" />
      <outline title="映画評論家町山智浩アメリカ日記" htmlUrl="http://d.hatena.ne.jp/TomoMachi/" type="rss" xmlUrl="http://d.hatena.ne.jp/TomoMachi/rss" />
      <outline title="海国防衛ジャーナル" htmlUrl="http://blog.livedoor.jp/nonreal-pompandcircumstance/" type="rss" xmlUrl="http://blog.livedoor.jp/nonreal-pompandcircumstance/index.rdf" />
      <outline title="himaginaryの日記" htmlUrl="http://d.hatena.ne.jp/himaginary/" type="rss" xmlUrl="http://d.hatena.ne.jp/himaginary/rss2" />
    </outline>
    <outline title="文化芸術宗教">
      <outline title="山形浩生の「経済のトリセツ」" htmlUrl="http://cruel.hatenablog.com/" type="rss" xmlUrl="http://cruel.hatenablog.com/feed" />
    </outline>
    <outline title="映画・ザ・ムービー">
      <outline title="メモリの藻屑、記憶領域のゴミ" htmlUrl="http://d.hatena.ne.jp/globalhead/" type="rss" xmlUrl="http://d.hatena.ne.jp/globalhead/rss" />
      <outline title="映画のブログ" htmlUrl="http://movieandtv.blog85.fc2.com/" type="rss" xmlUrl="http://movieandtv.blog85.fc2.com/?xml" />
      <outline title="びーきゅうらいふ！" htmlUrl="http://b9life.hatenablog.com/" type="rss" xmlUrl="http://b9life.hatenablog.com/feed" />
    </outline>
    <outline title="科学技術哲学">
      <outline title="WIRED.jp" htmlUrl="http://wired.jp" type="rss" xmlUrl="http://feed.rssad.jp/rss/wired/feed.rdf" />
      <outline title="檜山正幸のキマイラ飼育記" htmlUrl="http://d.hatena.ne.jp/m-hiyama/" type="rss" xmlUrl="http://d.hatena.ne.jp/m-hiyama/rss" />
      <outline title="shorebird　進化心理学中心の書評など" htmlUrl="http://d.hatena.ne.jp/shorebird/" type="rss" xmlUrl="http://d.hatena.ne.jp/shorebird/rss" />
      <outline title="とね日記" htmlUrl="http://blog.goo.ne.jp/ktonegaw?fm=rss" type="rss" xmlUrl="http://blog.goo.ne.jp/ktonegaw/rss2.xml" />
      <outline title="NATROMの日記" htmlUrl="http://d.hatena.ne.jp/NATROM/" type="rss" xmlUrl="http://d.hatena.ne.jp/NATROM/rss2" />
      <outline title="ありんこ日記　AntRoom" htmlUrl="http://blog.livedoor.jp/antroom/" type="rss" xmlUrl="http://blog.livedoor.jp/antroom/index.rdf" />
      <outline title="忘却からの帰還" htmlUrl="http://transact.seesaa.net/" type="rss" xmlUrl="http://transact.seesaa.net/index.rdf" />
      <outline title="科学に佇む一行読書の書斎" htmlUrl="http://sciencebook.blog110.fc2.com/" type="rss" xmlUrl="http://sciencebook.blog110.fc2.com/?xml" />
      <outline title="ibaibabaibaiのサイエンスブログ" htmlUrl="http://ibaibabaibai-h.hatenablog.com/" type="rss" xmlUrl="http://ibaibabaibai-h.hatenablog.com/feed" />
    </outline>
</outline>
</body></opml>
